src/__init__.py
src/ingest_data.py
src/score.py
src/train.py
Housing_pred-0.1.dist-info/METADATA
Housing_pred-0.1.dist-info/WHEEL
Housing_pred-0.1.dist-info/top_level.txt
Housing_pred-0.1.dist-info/RECORD
